pytest_yuk.py
pytest_yuk-0.0.1.post2.dist-info/entry_points.txt
pytest_yuk-0.0.1.post2.dist-info/LICENSE
pytest_yuk-0.0.1.post2.dist-info/WHEEL
pytest_yuk-0.0.1.post2.dist-info/METADATA
pytest_yuk-0.0.1.post2.dist-info/RECORD
